[
    {
        "ordenacao": 1,
        "Production": null,
        "State": null,
        "seccao": "Injecção",
        "maquina": "MI01 - 01 Krauss Maffei 650ton",
        "ocorrencia": "",
        "ofab": "",
        "etapa": "",
        "operadores": "",
        "produtos": "",
        "ciclo_prev": 0,
        "ciclo_real": 0,
        "Ciclo": "",
        "quant": "",
        "caixas": "",
        "fecho_caixas": "",
        "rejeitado_of": "",
        "rejeitado_of_val": "0%",
        "rejeitado_of_val1": 0,
        "rejeitado_prd": "",
        "rejeitado_prd_val": 0,
        "inicio": "",
        "fim": "",
        "progresso": "",
        "proximaOF": "",
        "proximaOM": "",
        "Estado_Dash": "Sem OF",
        "Contagem_Sem_OF": 12,
        "Contagem_Execucao": 21,
        "Contagem_Parada": 6,
        "Contagem_Em_Afinacao": 0
    },
    {
        "ordenacao": 2,
        "Production": null,
        "State": null,
        "seccao": "Injecção",
        "maquina": "MI07 - 07 Krauss Maffei 110ton",
        "ocorrencia": "",
        "ofab": "",
        "etapa": "",
        "operadores": "",
        "produtos": "",
        "ciclo_prev": 0,
        "ciclo_real": 0,
        "Ciclo": "",
        "quant": "",
        "caixas": "",
        "fecho_caixas": "",
        "rejeitado_of": "",
        "rejeitado_of_val": "0%",
        "rejeitado_of_val1": 0,
        "rejeitado_prd": "",
        "rejeitado_prd_val": 0,
        "inicio": "",
        "fim": "",
        "progresso": "",
        "proximaOF": "",
        "proximaOM": "",
        "Estado_Dash": "Sem OF",
        "Contagem_Sem_OF": 12,
        "Contagem_Execucao": 21,
        "Contagem_Parada": 6,
        "Contagem_Em_Afinacao": 0
    },
    {
        "ordenacao": 3,
        "Production": null,
        "State": null,
        "seccao": "Injecção",
        "maquina": "MI08 - 08 Ferromatik 200ton",
        "ocorrencia": "",
        "ofab": "",
        "etapa": "",
        "operadores": "",
        "produtos": "",
        "ciclo_prev": 0,
        "ciclo_real": 0,
        "Ciclo": "",
        "quant": "",
        "caixas": "",
        "fecho_caixas": "",
        "rejeitado_of": "",
        "rejeitado_of_val": "0%",
        "rejeitado_of_val1": 0,
        "rejeitado_prd": "",
        "rejeitado_prd_val": 0,
        "inicio": "",
        "fim": "",
        "progresso": "",
        "proximaOF": "OF05225/2024 - CORPO DA VALVULA JARDINARIA BSP - 2 A 180",
        "proximaOM": "",
        "Estado_Dash": "Sem OF",
        "Contagem_Sem_OF": 12,
        "Contagem_Execucao": 21,
        "Contagem_Parada": 6,
        "Contagem_Em_Afinacao": 0
    },
    {
        "ordenacao": 4,
        "Production": "PSS24102840979,559000024",
        "State": "P021",
        "seccao": "Injecção",
        "maquina": "MI09 - 09 Krauss Maffei 800ton",
        "ocorrencia": "Re-Afinação",
        "ofab": "OF05250/2024",
        "etapa": "Produção",
        "operadores": "Andre Costa<br> Eleuterio Mota",
        "produtos": "S100061052 - VASO SAN REMO MATE 36CM ANTRACITE",
        "ciclo_prev": 70,
        "ciclo_real": 110.019,
        "Ciclo": "P: 70,00 s / R: 110,02 s",
        "quant": "726 / 792",
        "caixas": "12",
        "fecho_caixas": "11 / 12",
        "rejeitado_of": "0,00% (0)",
        "rejeitado_of_val": "0%",
        "rejeitado_of_val1": 0,
        "rejeitado_prd": "0,00% (0)",
        "rejeitado_prd_val": 0,
        "inicio": "30.10.2024 13:08",
        "fim": "31.10.2024 13:20",
        "progresso": "91,67%",
        "proximaOF": "OF04141/2024 - COLECTOR ENT. CENTRAL UP15 PP",
        "proximaOM": "",
        "Estado_Dash": "Parada",
        "Contagem_Sem_OF": 12,
        "Contagem_Execucao": 21,
        "Contagem_Parada": 6,
        "Contagem_Em_Afinacao": 0
    },
    {
        "ordenacao": 5,
        "Production": "PSS24102841261,690000036",
        "State": "PRD",
        "seccao": "Injecção",
        "maquina": "MI10 - 10 Krauss Maffei 300 ton",
        "ocorrencia": "",
        "ofab": "OF05256/2024",
        "etapa": "Produção",
        "operadores": "Fabio Fresco",
        "produtos": "S100001262 - CORPO DO BEBEDOURO DE PLASTICO",
        "ciclo_prev": 140,
        "ciclo_real": 146.68,
        "Ciclo": "P: 140,00 s / R: 146,68 s",
        "quant": "399 / 500",
        "caixas": "2",
        "fecho_caixas": "1 / 1 (0)",
        "rejeitado_of": "3,39% (14)",
        "rejeitado_of_val": "3.4%",
        "rejeitado_of_val1": 0.03,
        "rejeitado_prd": "2,44% (10)",
        "rejeitado_prd_val": 2.44,
        "inicio": "29.10.2024 20:08",
        "fim": "31.10.2024 15:26",
        "progresso": "79,80%",
        "proximaOF": "OF04536/2024 - ARO SUPORTE PORTA MW22",
        "proximaOM": "",
        "Estado_Dash": "Execução",
        "Contagem_Sem_OF": 12,
        "Contagem_Execucao": 21,
        "Contagem_Parada": 6,
        "Contagem_Em_Afinacao": 0
    },
    {
        "ordenacao": 6,
        "Production": "PSS24103043775,885000026",
        "State": "PRD",
        "seccao": "Injecção",
        "maquina": "MI14 - 14 Krauss Maffei 50ton",
        "ocorrencia": "",
        "ofab": "OF05295/2024",
        "etapa": "Produção",
        "operadores": "Patricia Marques",
        "produtos": "S100006426 - POSTICO DIREITO II          ",
        "ciclo_prev": 20.84,
        "ciclo_real": 22.7,
        "Ciclo": "P: 20,84 s / R: 22,70 s",
        "quant": "4.835 / 12.000",
        "caixas": "20",
        "fecho_caixas": "5 / 8 (3)",
        "rejeitado_of": "2,36% (117)",
        "rejeitado_of_val": "2.4%",
        "rejeitado_of_val1": 0.02,
        "rejeitado_prd": "2,24% (111)",
        "rejeitado_prd_val": 2.24,
        "inicio": "30.10.2024 14:53",
        "fim": "01.11.2024 09:55",
        "progresso": "40,29%",
        "proximaOF": "",
        "proximaOM": "",
        "Estado_Dash": "Execução",
        "Contagem_Sem_OF": 12,
        "Contagem_Execucao": 21,
        "Contagem_Parada": 6,
        "Contagem_Em_Afinacao": 0
    },
    {
        "ordenacao": 7,
        "Production": null,
        "State": null,
        "seccao": "Injecção",
        "maquina": "MI15 - 15 Krauss Maffei 50ton",
        "ocorrencia": "",
        "ofab": "",
        "etapa": "",
        "operadores": "",
        "produtos": "",
        "ciclo_prev": 0,
        "ciclo_real": 0,
        "Ciclo": "",
        "quant": "",
        "caixas": "",
        "fecho_caixas": "",
        "rejeitado_of": "",
        "rejeitado_of_val": "0%",
        "rejeitado_of_val1": 0,
        "rejeitado_prd": "",
        "rejeitado_prd_val": 0,
        "inicio": "",
        "fim": "",
        "progresso": "",
        "proximaOF": "",
        "proximaOM": "",
        "Estado_Dash": "Sem OF",
        "Contagem_Sem_OF": 12,
        "Contagem_Execucao": 21,
        "Contagem_Parada": 6,
        "Contagem_Em_Afinacao": 0
    },
    {
        "ordenacao": 8,
        "Production": "PSS24102241298,171000022",
        "State": "PRD",
        "seccao": "Injecção",
        "maquina": "MI16 - 16 Ferromatik 275ton",
        "ocorrencia": "",
        "ofab": "OF05144/2024",
        "etapa": "Produção",
        "operadores": "Sergio G. Santos",
        "produtos": "S100012237 - FUNDO 400X375MM PSHI FR",
        "ciclo_prev": 24,
        "ciclo_real": 33.01,
        "Ciclo": "P: 24,00 s / R: 33,01 s",
        "quant": "8.153 / 12.272",
        "caixas": "236",
        "fecho_caixas": "155 / 156 (1)",
        "rejeitado_of": "0,66% (54)",
        "rejeitado_of_val": "0.7%",
        "rejeitado_of_val1": 0.01,
        "rejeitado_prd": "0,43% (35)",
        "rejeitado_prd_val": 0.43,
        "inicio": "24.10.2024 18:18",
        "fim": "02.11.2024 01:05",
        "progresso": "66,44%",
        "proximaOF": "OF05091/2024 - FUNDO 250X375MM PSHI FR",
        "proximaOM": "",
        "Estado_Dash": "Execução",
        "Contagem_Sem_OF": 12,
        "Contagem_Execucao": 21,
        "Contagem_Parada": 6,
        "Contagem_Em_Afinacao": 0
    },
    {
        "ordenacao": 9,
        "Production": "PSS24102932016,130000002",
        "State": "PRD",
        "seccao": "Injecção",
        "maquina": "MI17 - 17 Krauss Maffei 650ton",
        "ocorrencia": "",
        "ofab": "OF05266/2024",
        "etapa": "Desmontagem",
        "operadores": "",
        "produtos": "S100061157 - VASO SAN REMO 42 ANTRACITE BRILHO",
        "ciclo_prev": 75,
        "ciclo_real": 52.5,
        "Ciclo": "P: 75,00 s / R: 52,50 s",
        "quant": "388 / 384",
        "caixas": "128",
        "fecho_caixas": "129 / 129 (0)",
        "rejeitado_of": "5,83% (24)",
        "rejeitado_of_val": "5.8%",
        "rejeitado_of_val1": 0.06,
        "rejeitado_prd": "3,72% (15)",
        "rejeitado_prd_val": 3.72,
        "inicio": "30.10.2024 19:00",
        "fim": "",
        "progresso": "100,00%",
        "proximaOF": "",
        "proximaOM": "",
        "Estado_Dash": "Execução",
        "Contagem_Sem_OF": 12,
        "Contagem_Execucao": 21,
        "Contagem_Parada": 6,
        "Contagem_Em_Afinacao": 0
    },
    {
        "ordenacao": 10,
        "Production": null,
        "State": null,
        "seccao": "Injecção",
        "maquina": "MI18 - 18 Krauss Maffei 80ton",
        "ocorrencia": "",
        "ofab": "",
        "etapa": "",
        "operadores": "",
        "produtos": "",
        "ciclo_prev": 0,
        "ciclo_real": 0,
        "Ciclo": "",
        "quant": "",
        "caixas": "",
        "fecho_caixas": "",
        "rejeitado_of": "",
        "rejeitado_of_val": "0%",
        "rejeitado_of_val1": 0,
        "rejeitado_prd": "",
        "rejeitado_prd_val": 0,
        "inicio": "",
        "fim": "",
        "progresso": "",
        "proximaOF": "OF04769/2024 - CUERPO CARTUCHO R33M",
        "proximaOM": "",
        "Estado_Dash": "Sem OF",
        "Contagem_Sem_OF": 12,
        "Contagem_Execucao": 21,
        "Contagem_Parada": 6,
        "Contagem_Em_Afinacao": 0
    },
    {
        "ordenacao": 11,
        "Production": "PSS24103045953,281000002",
        "State": "PRD",
        "seccao": "Injecção",
        "maquina": "MI19 - 19 Krauss Maffei 40ton",
        "ocorrencia": "",
        "ofab": "OF05298/2024",
        "etapa": "Produção",
        "operadores": "Patricia Marques",
        "produtos": "S100012232 - PINO S/ FURO PSHI FR",
        "ciclo_prev": 17.6,
        "ciclo_real": 17.1,
        "Ciclo": "P: 17,60 s / R: 17,10 s",
        "quant": "28.161 / 140.000",
        "caixas": "14",
        "fecho_caixas": "2 / 2 (0)",
        "rejeitado_of": "1,84% (527)",
        "rejeitado_of_val": "1.8%",
        "rejeitado_of_val1": 0.02,
        "rejeitado_prd": "1,48% (423)",
        "rejeitado_prd_val": 1.48,
        "inicio": "30.10.2024 14:48",
        "fim": "03.11.2024 05:44",
        "progresso": "20,12%",
        "proximaOF": "OF05085/2024 - ALAVANCA INFERIOR MW 22 + ALAVANCA SUPERIOR MW 22",
        "proximaOM": "",
        "Estado_Dash": "Execução",
        "Contagem_Sem_OF": 12,
        "Contagem_Execucao": 21,
        "Contagem_Parada": 6,
        "Contagem_Em_Afinacao": 0
    },
    {
        "ordenacao": 12,
        "Production": null,
        "State": null,
        "seccao": "Injecção",
        "maquina": "MI20 - 20 Ferromatik 275ton",
        "ocorrencia": "",
        "ofab": "",
        "etapa": "",
        "operadores": "",
        "produtos": "",
        "ciclo_prev": 0,
        "ciclo_real": 0,
        "Ciclo": "",
        "quant": "",
        "caixas": "",
        "fecho_caixas": "",
        "rejeitado_of": "",
        "rejeitado_of_val": "0%",
        "rejeitado_of_val1": 0,
        "rejeitado_prd": "",
        "rejeitado_prd_val": 0,
        "inicio": "",
        "fim": "",
        "progresso": "",
        "proximaOF": "",
        "proximaOM": "",
        "Estado_Dash": "Sem OF",
        "Contagem_Sem_OF": 12,
        "Contagem_Execucao": 21,
        "Contagem_Parada": 6,
        "Contagem_Em_Afinacao": 0
    },
    {
        "ordenacao": 13,
        "Production": "PSS24102840606,249000010",
        "State": "PRD",
        "seccao": "Injecção",
        "maquina": "MI21 - 21 Krauss Maffei 125ton",
        "ocorrencia": "",
        "ofab": "OF05243/2024",
        "etapa": "Produção",
        "operadores": "Andreia Oliveira",
        "produtos": "S100001307 - TAMPA DA VALVULA C/ REGULADOR - 11/2",
        "ciclo_prev": 58.5,
        "ciclo_real": 60,
        "Ciclo": "P: 58,50 s / R: 60,00 s",
        "quant": "1.585 / 2.000",
        "caixas": "2",
        "fecho_caixas": "0 / 1 (1)",
        "rejeitado_of": "11,75% (211)",
        "rejeitado_of_val": "11.8%",
        "rejeitado_of_val1": 0.12,
        "rejeitado_prd": "10,55% (187)",
        "rejeitado_prd_val": 10.55,
        "inicio": "30.10.2024 00:36",
        "fim": "",
        "progresso": "79,25%",
        "proximaOF": "OF04405/2024 - CASQUILHO COLAGEM - 50MM X 1 1/2",
        "proximaOM": "",
        "Estado_Dash": "Execução",
        "Contagem_Sem_OF": 12,
        "Contagem_Execucao": 21,
        "Contagem_Parada": 6,
        "Contagem_Em_Afinacao": 0
    },
    {
        "ordenacao": 14,
        "Production": null,
        "State": null,
        "seccao": "Injecção",
        "maquina": "MI22 - 22 Krauss Maffei 125ton",
        "ocorrencia": "",
        "ofab": "",
        "etapa": "",
        "operadores": "",
        "produtos": "",
        "ciclo_prev": 0,
        "ciclo_real": 0,
        "Ciclo": "",
        "quant": "",
        "caixas": "",
        "fecho_caixas": "",
        "rejeitado_of": "",
        "rejeitado_of_val": "0%",
        "rejeitado_of_val1": 0,
        "rejeitado_prd": "",
        "rejeitado_prd_val": 0,
        "inicio": "",
        "fim": "",
        "progresso": "",
        "proximaOF": "OF05019/2024 - CONDUTA AR SAIDA MW 22",
        "proximaOM": "",
        "Estado_Dash": "Sem OF",
        "Contagem_Sem_OF": 12,
        "Contagem_Execucao": 21,
        "Contagem_Parada": 6,
        "Contagem_Em_Afinacao": 0
    },
    {
        "ordenacao": 15,
        "Production": "PSS24103123097,752000003",
        "State": "PRD",
        "seccao": "Injecção",
        "maquina": "MI23 - 23 Krauss Maffei 500ton",
        "ocorrencia": "",
        "ofab": "OF05304/2024",
        "etapa": "Produção",
        "operadores": "Lis Paola Aguilar",
        "produtos": "S100061176 - FLOREIRA CAPRI 50CM V2 TERRACOTA",
        "ciclo_prev": 45,
        "ciclo_real": 43.09,
        "Ciclo": "P: 45,00 s / R: 43,09 s",
        "quant": "153 / 384",
        "caixas": "2",
        "fecho_caixas": "0 / 0 (0)",
        "rejeitado_of": "0,00% (0)",
        "rejeitado_of_val": "0%",
        "rejeitado_of_val1": 0,
        "rejeitado_prd": "0,00% (0)",
        "rejeitado_prd_val": 0,
        "inicio": "31.10.2024 09:27",
        "fim": "31.10.2024 14:05",
        "progresso": "39,84%",
        "proximaOF": "OF04808/2024 - FLOREIRA CAPRI RA 50CM V2 VERDE CINZA",
        "proximaOM": "",
        "Estado_Dash": "Execução",
        "Contagem_Sem_OF": 12,
        "Contagem_Execucao": 21,
        "Contagem_Parada": 6,
        "Contagem_Em_Afinacao": 0
    },
    {
        "ordenacao": 16,
        "Production": null,
        "State": null,
        "seccao": "Injecção",
        "maquina": "MI24 - 24 Ferromatik E155",
        "ocorrencia": "",
        "ofab": "",
        "etapa": "",
        "operadores": "",
        "produtos": "",
        "ciclo_prev": 0,
        "ciclo_real": 0,
        "Ciclo": "",
        "quant": "",
        "caixas": "",
        "fecho_caixas": "",
        "rejeitado_of": "",
        "rejeitado_of_val": "0%",
        "rejeitado_of_val1": 0,
        "rejeitado_prd": "",
        "rejeitado_prd_val": 0,
        "inicio": "",
        "fim": "",
        "progresso": "",
        "proximaOF": "OF04420/2024 - LAMELAS P/ FILTRO 150MESH",
        "proximaOM": "",
        "Estado_Dash": "Sem OF",
        "Contagem_Sem_OF": 12,
        "Contagem_Execucao": 21,
        "Contagem_Parada": 6,
        "Contagem_Em_Afinacao": 0
    },
    {
        "ordenacao": 17,
        "Production": "PSS24102943601,372000014",
        "State": "PRD",
        "seccao": "Injecção",
        "maquina": "MI26 - 26 Krauss Maffei 420ton",
        "ocorrencia": "",
        "ofab": "OF05278/2024",
        "etapa": "Produção",
        "operadores": "Aderito Neto",
        "produtos": "S100009148 - TAPA LATERAL DF-100 PLASTICO",
        "ciclo_prev": 210,
        "ciclo_real": 182.36,
        "Ciclo": "P: 210,00 s / R: 182,36 s",
        "quant": "190 / 500",
        "caixas": "25",
        "fecho_caixas": "9 / 9 (0)",
        "rejeitado_of": "15,56% (35)",
        "rejeitado_of_val": "15.6%",
        "rejeitado_of_val1": 0.16,
        "rejeitado_prd": "14,41% (32)",
        "rejeitado_prd_val": 14.41,
        "inicio": "30.10.2024 16:03",
        "fim": "01.11.2024 03:01",
        "progresso": "38,00%",
        "proximaOF": "OF04864/2024 - ARO INTERNO PORTA MW22",
        "proximaOM": "",
        "Estado_Dash": "Execução",
        "Contagem_Sem_OF": 12,
        "Contagem_Execucao": 21,
        "Contagem_Parada": 6,
        "Contagem_Em_Afinacao": 0
    },
    {
        "ordenacao": 18,
        "Production": "PSS24103043269,900000006",
        "State": "PRD",
        "seccao": "Injecção",
        "maquina": "MI27 - 27 Krauss Maffei 200 ton",
        "ocorrencia": "",
        "ofab": "OF05285/2024",
        "etapa": "Produção",
        "operadores": "Andreina Mejias",
        "produtos": "S100065067 - HEADBAND U103 BLACK S/M PA ECO",
        "ciclo_prev": 29,
        "ciclo_real": 27.73,
        "Ciclo": "P: 29,00 s / R: 27,73 s",
        "quant": "420 / 1.000",
        "caixas": "2",
        "fecho_caixas": "0 / 0 (0)",
        "rejeitado_of": "54,84% (510)",
        "rejeitado_of_val": "54.8%",
        "rejeitado_of_val1": 0.55,
        "rejeitado_prd": "44,30% (334)",
        "rejeitado_prd_val": 44.3,
        "inicio": "31.10.2024 03:49",
        "fim": "31.10.2024 13:33",
        "progresso": "42,00%",
        "proximaOF": "OF04919/2024 - CUERPO DISTRIBUIDOR AIRE PM3/0",
        "proximaOM": "",
        "Estado_Dash": "Execução",
        "Contagem_Sem_OF": 12,
        "Contagem_Execucao": 21,
        "Contagem_Parada": 6,
        "Contagem_Em_Afinacao": 0
    },
    {
        "ordenacao": 19,
        "Production": "PSS24102342817,361000001",
        "State": "INT",
        "seccao": "Injecção",
        "maquina": "MI28 - 28 Krauss Maffei 50ton",
        "ocorrencia": "Paragem não justificada",
        "ofab": "OF05165/2024",
        "etapa": "Produção",
        "operadores": "",
        "produtos": "S100065128 - SV MECHANISM LATCH L<br>S100065129 - SV MECHANISM LATCH R",
        "ciclo_prev": 26.5,
        "ciclo_real": 45.31,
        "Ciclo": "P: 26,50 s / R: 45,31 s",
        "quant": "1.922 / 6.000<br>1.922 / 6.000",
        "caixas": "4<br>4",
        "fecho_caixas": "1 / 1 (0)<br>0 / 1 (1)",
        "rejeitado_of": "0,00% (0)<br>0,00% (0)",
        "rejeitado_of_val": "0%",
        "rejeitado_of_val1": 0,
        "rejeitado_prd": "0,00% (0)<br>0,00% (0)",
        "rejeitado_prd_val": 0,
        "inicio": "24.10.2024 22:53",
        "fim": "01.11.2024 12:59",
        "progresso": "32,03%",
        "proximaOF": "",
        "proximaOM": "",
        "Estado_Dash": "Parada",
        "Contagem_Sem_OF": 12,
        "Contagem_Execucao": 21,
        "Contagem_Parada": 6,
        "Contagem_Em_Afinacao": 0
    },
    {
        "ordenacao": 20,
        "Production": "PSS24102942288,461000001",
        "State": "PRD",
        "seccao": "Injecção",
        "maquina": "MI29 - 29 Krauss Maffei 50ton",
        "ocorrencia": "",
        "ofab": "OF05268/2024",
        "etapa": "Produção",
        "operadores": "Adriana Severino",
        "produtos": "S100012143 - CAIXA BARRAMENTO 23 FUROS VERDE",
        "ciclo_prev": 15.5,
        "ciclo_real": 18.49,
        "Ciclo": "P: 15,50 s / R: 18,49 s",
        "quant": "6.746 / 10.000",
        "caixas": "40",
        "fecho_caixas": "23 / 26 (3)",
        "rejeitado_of": "0,24% (16)",
        "rejeitado_of_val": "0.2%",
        "rejeitado_of_val1": 0,
        "rejeitado_prd": "0,12% (8)",
        "rejeitado_prd_val": 0.12,
        "inicio": "30.10.2024 05:14",
        "fim": "31.10.2024 19:41",
        "progresso": "67,46%",
        "proximaOF": "OF05015/2024 - X.COM INTERNAL FRAME L - XWED3 + X.COM INTERNAL FRAME R - XWED3",
        "proximaOM": "",
        "Estado_Dash": "Execução",
        "Contagem_Sem_OF": 12,
        "Contagem_Execucao": 21,
        "Contagem_Parada": 6,
        "Contagem_Em_Afinacao": 0
    },
    {
        "ordenacao": 21,
        "Production": "PSS24103043360,970000010",
        "State": "PRD",
        "seccao": "Injecção",
        "maquina": "MI30 - 30 Krauss Maffei 160ton",
        "ocorrencia": "",
        "ofab": "OF05287/2024",
        "etapa": "Produção",
        "operadores": "Natalia Almeida",
        "produtos": "S100061033 - VASO SAN REMO MATE 20CM ANTRACITE",
        "ciclo_prev": 43,
        "ciclo_real": 33.93,
        "Ciclo": "P: 43,00 s / R: 33,93 s",
        "quant": "1.659 / 2.304",
        "caixas": "4",
        "fecho_caixas": "2 / 2 (0)",
        "rejeitado_of": "4,87% (85)",
        "rejeitado_of_val": "4.9%",
        "rejeitado_of_val1": 0.05,
        "rejeitado_prd": "4,60% (80)",
        "rejeitado_prd_val": 4.6,
        "inicio": "",
        "fim": "31.10.2024 17:24",
        "progresso": "72,01%",
        "proximaOF": "",
        "proximaOM": "",
        "Estado_Dash": "Execução",
        "Contagem_Sem_OF": 12,
        "Contagem_Execucao": 21,
        "Contagem_Parada": 6,
        "Contagem_Em_Afinacao": 0
    },
    {
        "ordenacao": 22,
        "Production": null,
        "State": null,
        "seccao": "Injecção",
        "maquina": "MI31 - 31 Krauss Maffei 50ton",
        "ocorrencia": "",
        "ofab": "",
        "etapa": "",
        "operadores": "",
        "produtos": "",
        "ciclo_prev": 0,
        "ciclo_real": 0,
        "Ciclo": "",
        "quant": "",
        "caixas": "",
        "fecho_caixas": "",
        "rejeitado_of": "",
        "rejeitado_of_val": "0%",
        "rejeitado_of_val1": 0,
        "rejeitado_prd": "",
        "rejeitado_prd_val": 0,
        "inicio": "",
        "fim": "",
        "progresso": "",
        "proximaOF": "",
        "proximaOM": "",
        "Estado_Dash": "Sem OF",
        "Contagem_Sem_OF": 12,
        "Contagem_Execucao": 21,
        "Contagem_Parada": 6,
        "Contagem_Em_Afinacao": 0
    },
    {
        "ordenacao": 23,
        "Production": null,
        "State": null,
        "seccao": "Injecção",
        "maquina": "MI32 - 32 Krauss Maffei 50ton",
        "ocorrencia": "",
        "ofab": "",
        "etapa": "",
        "operadores": "",
        "produtos": "",
        "ciclo_prev": 0,
        "ciclo_real": 0,
        "Ciclo": "",
        "quant": "",
        "caixas": "",
        "fecho_caixas": "",
        "rejeitado_of": "",
        "rejeitado_of_val": "0%",
        "rejeitado_of_val1": 0,
        "rejeitado_prd": "",
        "rejeitado_prd_val": 0,
        "inicio": "",
        "fim": "",
        "progresso": "",
        "proximaOF": "",
        "proximaOM": "",
        "Estado_Dash": "Sem OF",
        "Contagem_Sem_OF": 12,
        "Contagem_Execucao": 21,
        "Contagem_Parada": 6,
        "Contagem_Em_Afinacao": 0
    },
    {
        "ordenacao": 24,
        "Production": "PSS24102943340,710000004",
        "State": "PRD",
        "seccao": "Injecção",
        "maquina": "MI33 - 33 Krauss Maffei 130ton",
        "ocorrencia": "",
        "ofab": "OF05273/2024",
        "etapa": "Produção",
        "operadores": "Natalia Almeida",
        "produtos": "S100061024 - VASO SAN REMO MATE 16CM VERDE SECO",
        "ciclo_prev": 27,
        "ciclo_real": 29.59,
        "Ciclo": "P: 27,00 s / R: 29,59 s",
        "quant": "1.258 / 1.944",
        "caixas": "3",
        "fecho_caixas": "1 / 1 (0)",
        "rejeitado_of": "1,41% (18)",
        "rejeitado_of_val": "1.4%",
        "rejeitado_of_val1": 0.01,
        "rejeitado_prd": "0,00% (0)",
        "rejeitado_prd_val": 0,
        "inicio": "31.10.2024 00:50",
        "fim": "31.10.2024 16:58",
        "progresso": "64,71%",
        "proximaOF": "OF03321/2024 - TAMPA QUAD D 20MD 405X125MM PSHI FR",
        "proximaOM": "",
        "Estado_Dash": "Execução",
        "Contagem_Sem_OF": 12,
        "Contagem_Execucao": 21,
        "Contagem_Parada": 6,
        "Contagem_Em_Afinacao": 0
    },
    {
        "ordenacao": 25,
        "Production": "PSS24102345579,014000008",
        "State": "PRD",
        "seccao": "Injecção",
        "maquina": "MI34 - 34 Krauss Maffei 300ton",
        "ocorrencia": "",
        "ofab": "OF05170/2024",
        "etapa": "Produção",
        "operadores": "Viviane Oliveira",
        "produtos": "S100061150 - VASO SAN REMO 30 BRANCO BRILHO",
        "ciclo_prev": 48,
        "ciclo_real": 52.76,
        "Ciclo": "P: 48,00 s / R: 52,76 s",
        "quant": "2.521 / 3.080",
        "caixas": "20",
        "fecho_caixas": "16 / 16 (0)",
        "rejeitado_of": "1,06% (27)",
        "rejeitado_of_val": "1.1%",
        "rejeitado_of_val1": 0.01,
        "rejeitado_prd": "1,06% (27)",
        "rejeitado_prd_val": 1.06,
        "inicio": "29.10.2024 23:09",
        "fim": "31.10.2024 19:31",
        "progresso": "81,85%",
        "proximaOF": "OF05169/2024 - VASO SAN REMO 30 BRANCO BR - SWS",
        "proximaOM": "",
        "Estado_Dash": "Execução",
        "Contagem_Sem_OF": 12,
        "Contagem_Execucao": 21,
        "Contagem_Parada": 6,
        "Contagem_Em_Afinacao": 0
    },
    {
        "ordenacao": 26,
        "Production": null,
        "State": null,
        "seccao": "Injecção",
        "maquina": "MI35 - 35 Ferromatik EE230",
        "ocorrencia": "",
        "ofab": "",
        "etapa": "",
        "operadores": "",
        "produtos": "",
        "ciclo_prev": 0,
        "ciclo_real": 0,
        "Ciclo": "",
        "quant": "",
        "caixas": "",
        "fecho_caixas": "",
        "rejeitado_of": "",
        "rejeitado_of_val": "0%",
        "rejeitado_of_val1": 0,
        "rejeitado_prd": "",
        "rejeitado_prd_val": 0,
        "inicio": "",
        "fim": "",
        "progresso": "",
        "proximaOF": "",
        "proximaOM": "",
        "Estado_Dash": "Sem OF",
        "Contagem_Sem_OF": 12,
        "Contagem_Execucao": 21,
        "Contagem_Parada": 6,
        "Contagem_Em_Afinacao": 0
    },
    {
        "ordenacao": 27,
        "Production": "PSS24102840724,053000016",
        "State": "PRD",
        "seccao": "Injecção",
        "maquina": "MI36 - 36 Ferromatik EE180",
        "ocorrencia": "",
        "ofab": "OF05246/2024",
        "etapa": "Produção",
        "operadores": "Sergio G. Santos",
        "produtos": "S140061032 - PRATO CAPRI LARGO RA 35CM ANTRACITE",
        "ciclo_prev": 29.5,
        "ciclo_real": 30.4,
        "Ciclo": "P: 29,50 s / R: 30,40 s",
        "quant": "3.119 / 3.260",
        "caixas": "163",
        "fecho_caixas": "155 / 155 (0)",
        "rejeitado_of": "4,03% (131)",
        "rejeitado_of_val": "4%",
        "rejeitado_of_val1": 0.04,
        "rejeitado_prd": "2,47% (79)",
        "rejeitado_prd_val": 2.47,
        "inicio": "29.10.2024 23:07",
        "fim": "31.10.2024 12:31",
        "progresso": "95,68%",
        "proximaOF": "OF05296/2024 - ARMELHENE 837A PC",
        "proximaOM": "",
        "Estado_Dash": "Execução",
        "Contagem_Sem_OF": 12,
        "Contagem_Execucao": 21,
        "Contagem_Parada": 6,
        "Contagem_Em_Afinacao": 0
    },
    {
        "ordenacao": 28,
        "Production": "PSS24102544540,530000032",
        "State": "PRD",
        "seccao": "Injecção",
        "maquina": "MI37 - 37 Ferromatik EE155",
        "ocorrencia": "",
        "ofab": "OF05223/2024",
        "etapa": "Produção",
        "operadores": "Andreia Oliveira",
        "produtos": "S140061017 - PRATO CAPRI LARGO RA 20CM ANTRACITE",
        "ciclo_prev": 29.9,
        "ciclo_real": 29.708,
        "Ciclo": "P: 29,90 s / R: 29,71 s",
        "quant": "6.480 / 8.080",
        "caixas": "101",
        "fecho_caixas": "81 / 101",
        "rejeitado_of": "3,25% (218)",
        "rejeitado_of_val": "3.3%",
        "rejeitado_of_val1": 0.03,
        "rejeitado_prd": "2,06% (136)",
        "rejeitado_prd_val": 2.06,
        "inicio": "29.10.2024 03:57",
        "fim": "01.11.2024 00:31",
        "progresso": "80,20%",
        "proximaOF": "OF05068/2024 - EMBELEZADOR CLASSIC DIREITO PRETO + EMBELEZADOR CLASSIC ESQUERDO PR",
        "proximaOM": "",
        "Estado_Dash": "Execução",
        "Contagem_Sem_OF": 12,
        "Contagem_Execucao": 21,
        "Contagem_Parada": 6,
        "Contagem_Em_Afinacao": 0
    },
    {
        "ordenacao": 29,
        "Production": "PSS24102434093,450000006",
        "State": "INT",
        "seccao": "Injecção",
        "maquina": "MI38 - 38 Krauss Maffei 80 / 380 CX",
        "ocorrencia": "Paragem não justificada",
        "ofab": "OF05201/2024",
        "etapa": "Produção",
        "operadores": "",
        "produtos": "S100065144 - TOP VENTILATION FRAME BLACK - X. LIFETOUR",
        "ciclo_prev": 25,
        "ciclo_real": 27.61,
        "Ciclo": "P: 25,00 s / R: 27,61 s",
        "quant": "4.226 / 4.000",
        "caixas": "15",
        "fecho_caixas": "16 / 16 (0)",
        "rejeitado_of": "2,81% (122)",
        "rejeitado_of_val": "2.8%",
        "rejeitado_of_val1": 0.03,
        "rejeitado_prd": "0,42% (18)",
        "rejeitado_prd_val": 0.42,
        "inicio": "25.10.2024 01:33",
        "fim": "",
        "progresso": "100,00%",
        "proximaOF": "OF04630/2024 - TRINQUETE ENROLLADOR MONOBRAZO",
        "proximaOM": "",
        "Estado_Dash": "Parada",
        "Contagem_Sem_OF": 12,
        "Contagem_Execucao": 21,
        "Contagem_Parada": 6,
        "Contagem_Em_Afinacao": 0
    },
    {
        "ordenacao": 30,
        "Production": "PSS24102840549,496000008",
        "State": "PRD",
        "seccao": "Injecção",
        "maquina": "MI39 - 39 Krauss Maffei 80 / 750 CX",
        "ocorrencia": "",
        "ofab": "OF05242/2024",
        "etapa": "Produção",
        "operadores": "",
        "produtos": "S100065054 - HEADBASKET U103 BLACK PA ECO",
        "ciclo_prev": 30,
        "ciclo_real": 28.32,
        "Ciclo": "P: 30,00 s / R: 28,32 s",
        "quant": "35 / 2.100",
        "caixas": "14",
        "fecho_caixas": "0 / 0 (0)",
        "rejeitado_of": "74,64% (103)",
        "rejeitado_of_val": "74.6%",
        "rejeitado_of_val1": 0.75,
        "rejeitado_prd": "0,00% (0)",
        "rejeitado_prd_val": 0,
        "inicio": "30.10.2024 05:33",
        "fim": "01.11.2024 03:34",
        "progresso": "1,67%",
        "proximaOF": "OF04409/2024 - ANEL DE APOIO DA MEMBRANA - 11/2",
        "proximaOM": "",
        "Estado_Dash": "Execução",
        "Contagem_Sem_OF": 12,
        "Contagem_Execucao": 21,
        "Contagem_Parada": 6,
        "Contagem_Em_Afinacao": 0
    },
    {
        "ordenacao": 31,
        "Production": "PSS24103043707,090000022",
        "State": "PRD",
        "seccao": "Injecção",
        "maquina": "MI40 - 40 Krauss Maffei 450 - 3000 GX",
        "ocorrencia": "",
        "ofab": "OF05293/2024",
        "etapa": "Produção",
        "operadores": "Joni Santos",
        "produtos": "S100061041 - VASO SAN REMO MATE 25CM ANTRACITE",
        "ciclo_prev": 43,
        "ciclo_real": 35.17,
        "Ciclo": "P: 43,00 s / R: 35,17 s",
        "quant": "1.130 / 6.480",
        "caixas": "30",
        "fecho_caixas": "5 / 5 (0)",
        "rejeitado_of": "3,99% (47)",
        "rejeitado_of_val": "4%",
        "rejeitado_of_val1": 0.04,
        "rejeitado_prd": "0,53% (6)",
        "rejeitado_prd_val": 0.53,
        "inicio": "30.10.2024 22:54",
        "fim": "02.11.2024 15:35",
        "progresso": "17,44%",
        "proximaOF": "OF04257/2024 - PLASTRON 299,5X754 PLEIN",
        "proximaOM": "",
        "Estado_Dash": "Execução",
        "Contagem_Sem_OF": 12,
        "Contagem_Execucao": 21,
        "Contagem_Parada": 6,
        "Contagem_Em_Afinacao": 0
    },
    {
        "ordenacao": 32,
        "Production": "PSS24102943258,249000002",
        "State": "PRD",
        "seccao": "Injecção",
        "maquina": "MI41 - 41 Krauss Maffei 50 / 380 CX",
        "ocorrencia": "",
        "ofab": "OF05271/2024",
        "etapa": "Produção",
        "operadores": "Adriana Severino",
        "produtos": "S100013022 - PIVOTE CARTUCHO R37 NATURAL",
        "ciclo_prev": 30.78,
        "ciclo_real": 32.259,
        "Ciclo": "P: 30,78 s / R: 32,26 s",
        "quant": "23.612 / 50.000",
        "caixas": "20",
        "fecho_caixas": "9 / 9 (0)",
        "rejeitado_of": "1,85% (444)",
        "rejeitado_of_val": "1.9%",
        "rejeitado_of_val1": 0.02,
        "rejeitado_prd": "0,08% (20)",
        "rejeitado_prd_val": 0.08,
        "inicio": "30.10.2024 04:30",
        "fim": "01.11.2024 16:53",
        "progresso": "47,22%",
        "proximaOF": "OF01727/2023 - SV MECHANISM FRAME L+R\u0002",
        "proximaOM": "",
        "Estado_Dash": "Execução",
        "Contagem_Sem_OF": 12,
        "Contagem_Execucao": 21,
        "Contagem_Parada": 6,
        "Contagem_Em_Afinacao": 0
    },
    {
        "ordenacao": 33,
        "Production": "PSS24101832534,834000010",
        "State": "P028",
        "seccao": "Injecção",
        "maquina": "MI42 - 42 Krauss Maffei 300 / 2000 CX",
        "ocorrencia": "Fim de Produção",
        "ofab": "OF05093/2024",
        "etapa": "Produção",
        "operadores": "",
        "produtos": "S100012198 - FUNDO TRANSPARENTE SUPERIOR EB_BOX<br>S100012199 - FUNDO TRANSPARENTE INFERIOR EB_BOX",
        "ciclo_prev": 52.12,
        "ciclo_real": 47.74,
        "Ciclo": "P: 52,12 s / R: 47,74 s",
        "quant": "5.515 / 5.440<br>5.856 / 5.440",
        "caixas": "151<br>175",
        "fecho_caixas": "151 / 153 (2)<br>187 / 188 (1)",
        "rejeitado_of": "21,63% (1.522)<br>16,78% (1.181)",
        "rejeitado_of_val": "21.6%",
        "rejeitado_of_val1": 0.22,
        "rejeitado_prd": "20,19% (1.395)<br>15,25% (1.054)",
        "rejeitado_prd_val": 20.19,
        "inicio": "18.10.2024 19:02",
        "fim": "",
        "progresso": "100,00%",
        "proximaOF": "OF05229/2024 - TOPO 475X125MM PSHI FR",
        "proximaOM": "",
        "Estado_Dash": "Parada",
        "Contagem_Sem_OF": 12,
        "Contagem_Execucao": 21,
        "Contagem_Parada": 6,
        "Contagem_Em_Afinacao": 0
    },
    {
        "ordenacao": 34,
        "Production": "PSS24102943483,416000010",
        "State": "PRD",
        "seccao": "Injecção",
        "maquina": "MI43 - 43 Krauss Maffei 500 - 3000 GX",
        "ocorrencia": "",
        "ofab": "OF05276/2024",
        "etapa": "Produção",
        "operadores": "Carla Rocha",
        "produtos": "S100033013 - SIDEWING LH<br>S100033014 - SIDEWING RH",
        "ciclo_prev": 40.3,
        "ciclo_real": 40.35,
        "Ciclo": "P: 40,30 s / R: 40,35 s",
        "quant": "877 / 6.375<br>877 / 6.375",
        "caixas": "425<br>425",
        "fecho_caixas": "56 / 58 (2)<br>56 / 58 (2)",
        "rejeitado_of": "1,68% (15)<br>1,68% (15)",
        "rejeitado_of_val": "1.7%",
        "rejeitado_of_val1": 0.02,
        "rejeitado_prd": "0,00% (0)<br>0,00% (0)",
        "rejeitado_prd_val": 0,
        "inicio": "30.10.2024 23:14",
        "fim": "03.11.2024 00:57",
        "progresso": "13,76%",
        "proximaOF": "",
        "proximaOM": "",
        "Estado_Dash": "Execução",
        "Contagem_Sem_OF": 12,
        "Contagem_Execucao": 21,
        "Contagem_Parada": 6,
        "Contagem_Em_Afinacao": 0
    },
    {
        "ordenacao": 35,
        "Production": "PSS24103123222,561000005",
        "State": "P009",
        "seccao": "Injecção",
        "maquina": "MI44 - 44 Krauss Maffei 1150",
        "ocorrencia": "Espera Afinador",
        "ofab": "OF05305/2024",
        "etapa": "Afinação",
        "operadores": "",
        "produtos": "S140005129 - CASCO X68 PC - GRANDE",
        "ciclo_prev": 115,
        "ciclo_real": 58.52,
        "Ciclo": "P: 115,00 s / R: 58,52 s",
        "quant": "0 / 5.000",
        "caixas": "52",
        "fecho_caixas": "0 / 0 (0)",
        "rejeitado_of": "0,00% (0)",
        "rejeitado_of_val": "0%",
        "rejeitado_of_val1": 0,
        "rejeitado_prd": "0,00% (0)",
        "rejeitado_prd_val": 0,
        "inicio": "31.10.2024 08:04",
        "fim": "",
        "progresso": "0,00%",
        "proximaOF": "OF05037/2024 - VASO CAPRI LARGO RA 50CM BRANCO",
        "proximaOM": "",
        "Estado_Dash": "Parada",
        "Contagem_Sem_OF": 12,
        "Contagem_Execucao": 21,
        "Contagem_Parada": 6,
        "Contagem_Em_Afinacao": 0
    },
    {
        "ordenacao": 36,
        "Production": null,
        "State": null,
        "seccao": "Injecção",
        "maquina": "MI45 - 45 Engel 100",
        "ocorrencia": "",
        "ofab": "",
        "etapa": "",
        "operadores": "",
        "produtos": "",
        "ciclo_prev": 0,
        "ciclo_real": 0,
        "Ciclo": "",
        "quant": "",
        "caixas": "",
        "fecho_caixas": "",
        "rejeitado_of": "",
        "rejeitado_of_val": "0%",
        "rejeitado_of_val1": 0,
        "rejeitado_prd": "",
        "rejeitado_prd_val": 0,
        "inicio": "",
        "fim": "",
        "progresso": "",
        "proximaOF": "",
        "proximaOM": "",
        "Estado_Dash": "Sem OF",
        "Contagem_Sem_OF": 12,
        "Contagem_Execucao": 21,
        "Contagem_Parada": 6,
        "Contagem_Em_Afinacao": 0
    },
    {
        "ordenacao": 37,
        "Production": "PSS24102434887,020000008",
        "State": "PRD",
        "seccao": "Injecção",
        "maquina": "MI46 - 46 Krauss Maffei 500ton",
        "ocorrencia": "",
        "ofab": "OF05202/2024",
        "etapa": "Produção",
        "operadores": "Silvia Campos",
        "produtos": "S100033012 - HEADREST FRAME",
        "ciclo_prev": 52.66,
        "ciclo_real": 54.37,
        "Ciclo": "P: 52,66 s / R: 54,37 s",
        "quant": "1.120 / 3.570",
        "caixas": "35",
        "fecho_caixas": "10 / 10 (0)",
        "rejeitado_of": "4,60% (54)",
        "rejeitado_of_val": "4.6%",
        "rejeitado_of_val1": 0.05,
        "rejeitado_prd": "3,20% (37)",
        "rejeitado_prd_val": 3.2,
        "inicio": "30.10.2024 13:04",
        "fim": "02.11.2024 00:19",
        "progresso": "31,37%",
        "proximaOF": "",
        "proximaOM": "",
        "Estado_Dash": "Execução",
        "Contagem_Sem_OF": 12,
        "Contagem_Execucao": 21,
        "Contagem_Parada": 6,
        "Contagem_Em_Afinacao": 0
    },
    {
        "ordenacao": 38,
        "Production": "PSS24101651499,524000010",
        "State": "P016",
        "seccao": "Injecção",
        "maquina": "MI47 - 47 ENGEL 400ton",
        "ocorrencia": "Falta Operador",
        "ofab": "OF05031/2024",
        "etapa": "Afinação",
        "operadores": "",
        "produtos": "S140061041 - PRATO CAPRI LARGO RA 50CM BRANCO",
        "ciclo_prev": 48.1,
        "ciclo_real": 53.24,
        "Ciclo": "P: 48,10 s / R: 53,24 s",
        "quant": "22 / 420",
        "caixas": "12",
        "fecho_caixas": "0 / 0 (0)",
        "rejeitado_of": "0,00% (0)",
        "rejeitado_of_val": "0%",
        "rejeitado_of_val1": 0,
        "rejeitado_prd": "0,00% (0)",
        "rejeitado_prd_val": 0,
        "inicio": "30.10.2024 01:30",
        "fim": "",
        "progresso": "20,00%",
        "proximaOF": "OF04809/2024 - VASO CAPRI LARGO RA 25CM ANTRACITE",
        "proximaOM": "",
        "Estado_Dash": "Parada",
        "Contagem_Sem_OF": 12,
        "Contagem_Execucao": 21,
        "Contagem_Parada": 6,
        "Contagem_Em_Afinacao": 0
    },
    {
        "ordenacao": 39,
        "Production": "PSS24101651149,123000002",
        "State": "PRD",
        "seccao": "Injecção",
        "maquina": "MI48 - 48 ENGEL 500ton",
        "ocorrencia": "",
        "ofab": "OF05027/2024",
        "etapa": "Produção",
        "operadores": "Alice Barreira",
        "produtos": "S100061179 - VASO MADAGASCAR PRODUCAO 30 MA VERDE SECO",
        "ciclo_prev": 30,
        "ciclo_real": 28.84,
        "Ciclo": "P: 30,00 s / R: 28,84 s",
        "quant": "3.210 / 3.240",
        "caixas": "3",
        "fecho_caixas": "2 / 2 (0)",
        "rejeitado_of": "1,71% (56)",
        "rejeitado_of_val": "1.7%",
        "rejeitado_of_val1": 0.02,
        "rejeitado_prd": "1,35% (44)",
        "rejeitado_prd_val": 1.35,
        "inicio": "16.10.2024 20:41",
        "fim": "31.10.2024 11:34",
        "progresso": "99,07%",
        "proximaOF": "OF05071/2024 - VASO MADAGASCAR PRODUCAO 30 MA TERRACOTA",
        "proximaOM": "",
        "Estado_Dash": "Execução",
        "Contagem_Sem_OF": 12,
        "Contagem_Execucao": 21,
        "Contagem_Parada": 6,
        "Contagem_Em_Afinacao": 0
    }
]